{
  "coord": {
    "lon": -77.0364,
    "lat": 38.8951
  },
  "weather": [
    {
      "id": 801,
      "main": "Clouds",
      "description": "few clouds",
      "icon": "02n"
    }
  ],
  "base": "stations",
  "main": {
    "temp": 283.43,
    "feels_like": 282.79,
    "temp_min": 279.73,
    "temp_max": 286.23,
    "pressure": 1023,
    "humidity": 87
  },
  "visibility": 10000,
  "wind": {
    "speed": 2.06,
    "deg": 30
  },
  "clouds": {
    "all": 20
  },
  "dt": 1636611474,
  "sys": {
    "type": 2,
    "id": 2007789,
    "country": "US",
    "sunrise": 1636631203,
    "sunset": 1636667870
  },
  "timezone": -18000,
  "id": 4140963,
  "name": "Washington D.C.",
  "cod": 200
}
