{
  "coord": {
    "lon": -77.0364,
    "lat": 38.8951
  },
  "weather": [
    {
      "id": 801,
      "main": "Clouds",
      "description": "few clouds",
      "icon": "02n"
    }
  ],
  "base": "stations",
  "main": {
    "temp": 293.12,
    "feels_like": 293,
    "temp_min": 290.63,
    "temp_max": 294.74,
    "pressure": 1010,
    "humidity": 70
  },
  "visibility": 10000,
  "wind": {
    "speed": 2.24,
    "deg": 103,
    "gust": 6.26
  },
  "clouds": {
    "all": 20
  },
  "dt": 1634868371,
  "sys": {
    "type": 2,
    "id": 2002287,
    "country": "US",
    "sunrise": 1634815423,
    "sunset": 1634854884
  },
  "timezone": -14400,
  "id": 4140963,
  "name": "Washington D.C.",
  "cod": 200
}
