{
  "coord": {
    "lon": -77.0364,
    "lat": 38.8951
  },
  "weather": [
    {
      "id": 804,
      "main": "Clouds",
      "description": "overcast clouds",
      "icon": "04n"
    }
  ],
  "base": "stations",
  "main": {
    "temp": 275.15,
    "feels_like": 275.15,
    "temp_min": 271.68,
    "temp_max": 278.44,
    "pressure": 1009,
    "humidity": 87
  },
  "visibility": 10000,
  "wind": {
    "speed": 0.45,
    "deg": 288,
    "gust": 0.45
  },
  "clouds": {
    "all": 90
  },
  "dt": 1641460466,
  "sys": {
    "type": 2,
    "id": 2002287,
    "country": "US",
    "sunrise": 1641472015,
    "sunset": 1641506442
  },
  "timezone": -18000,
  "id": 4140963,
  "name": "Washington D.C.",
  "cod": 200
}
