{
  "coord": {
    "lon": -77.0364,
    "lat": 38.8951
  },
  "weather": [
    {
      "id": 804,
      "main": "Clouds",
      "description": "overcast clouds",
      "icon": "04d"
    }
  ],
  "base": "stations",
  "main": {
    "temp": 295.51,
    "feels_like": 296.15,
    "temp_min": 294.01,
    "temp_max": 296.78,
    "pressure": 1021,
    "humidity": 90
  },
  "visibility": 10000,
  "wind": {
    "speed": 0.45,
    "deg": 33,
    "gust": 2.68
  },
  "clouds": {
    "all": 90
  },
  "dt": 1630235461,
  "sys": {
    "type": 2,
    "id": 2002287,
    "country": "US",
    "sunrise": 1630233287,
    "sunset": 1630280619
  },
  "timezone": -14400,
  "id": 4140963,
  "name": "Washington D.C.",
  "cod": 200
}
