{
  "coord": {
    "lon": -77.0364,
    "lat": 38.8951
  },
  "weather": [
    {
      "id": 802,
      "main": "Clouds",
      "description": "scattered clouds",
      "icon": "03n"
    }
  ],
  "base": "stations",
  "main": {
    "temp": 301.57,
    "feels_like": 305.62,
    "temp_min": 297.65,
    "temp_max": 303.83,
    "pressure": 1019,
    "humidity": 76
  },
  "visibility": 10000,
  "wind": {
    "speed": 1.34,
    "deg": 128,
    "gust": 4.47
  },
  "clouds": {
    "all": 40
  },
  "dt": 1626143234,
  "sys": {
    "type": 2,
    "id": 2002287,
    "country": "US",
    "sunrise": 1626083579,
    "sunset": 1626136453
  },
  "timezone": -14400,
  "id": 4140963,
  "name": "Washington D.C.",
  "cod": 200
}
