{
  "coord": {
    "lon": -77.0364,
    "lat": 38.8951
  },
  "weather": [
    {
      "id": 801,
      "main": "Clouds",
      "description": "few clouds",
      "icon": "02n"
    }
  ],
  "base": "stations",
  "main": {
    "temp": 284.23,
    "feels_like": 283.77,
    "temp_min": 281.26,
    "temp_max": 286.4,
    "pressure": 1017,
    "humidity": 91
  },
  "visibility": 10000,
  "wind": {
    "speed": 2.57,
    "deg": 330
  },
  "clouds": {
    "all": 20
  },
  "dt": 1632478259,
  "sys": {
    "type": 2,
    "id": 2040304,
    "country": "US",
    "sunrise": 1632481069,
    "sunset": 1632524539
  },
  "timezone": -14400,
  "id": 4140963,
  "name": "Washington D.C.",
  "cod": 200
}
