{
  "coord": {
    "lon": -77.0364,
    "lat": 38.8951
  },
  "weather": [
    {
      "id": 804,
      "main": "Clouds",
      "description": "overcast clouds",
      "icon": "04n"
    }
  ],
  "base": "stations",
  "main": {
    "temp": 283.08,
    "feels_like": 279.67,
    "temp_min": 280.65,
    "temp_max": 284.82,
    "pressure": 1012,
    "humidity": 55
  },
  "visibility": 10000,
  "wind": {
    "speed": 8.23,
    "deg": 310,
    "gust": 19.55
  },
  "clouds": {
    "all": 100
  },
  "dt": 1646719588,
  "sys": {
    "type": 2,
    "id": 2002287,
    "country": "US",
    "sunrise": 1646739022,
    "sunset": 1646780863
  },
  "timezone": -18000,
  "id": 4140963,
  "name": "Washington D.C.",
  "cod": 200
}
