{
  "coord": {
    "lon": -77.0364,
    "lat": 38.8951
  },
  "weather": [
    {
      "id": 803,
      "main": "Clouds",
      "description": "broken clouds",
      "icon": "04d"
    }
  ],
  "base": "stations",
  "main": {
    "temp": 304.66,
    "feels_like": 307.55,
    "temp_min": 302.44,
    "temp_max": 306.53,
    "pressure": 1012,
    "humidity": 54
  },
  "visibility": 10000,
  "wind": {
    "speed": 2.24,
    "deg": 85,
    "gust": 5.81
  },
  "clouds": {
    "all": 75
  },
  "dt": 1631729607,
  "sys": {
    "type": 2,
    "id": 2002287,
    "country": "US",
    "sunrise": 1631702990,
    "sunset": 1631747815
  },
  "timezone": -14400,
  "id": 4140963,
  "name": "Washington D.C.",
  "cod": 200
}
