{
  "coord": {
    "lon": -77.0364,
    "lat": 38.8951
  },
  "weather": [
    {
      "id": 803,
      "main": "Clouds",
      "description": "broken clouds",
      "icon": "04n"
    }
  ],
  "base": "stations",
  "main": {
    "temp": 282.8,
    "feels_like": 280.67,
    "temp_min": 281.04,
    "temp_max": 284.18,
    "pressure": 1018,
    "humidity": 53
  },
  "visibility": 10000,
  "wind": {
    "speed": 4.12,
    "deg": 300
  },
  "clouds": {
    "all": 75
  },
  "dt": 1647836386,
  "sys": {
    "type": 2,
    "id": 2002287,
    "country": "US",
    "sunrise": 1647861003,
    "sunset": 1647904831
  },
  "timezone": -14400,
  "id": 4140963,
  "name": "Washington D.C.",
  "cod": 200
}
