{
  "coord": {
    "lon": -77.0364,
    "lat": 38.8951
  },
  "weather": [
    {
      "id": 801,
      "main": "Clouds",
      "description": "few clouds",
      "icon": "02n"
    }
  ],
  "base": "stations",
  "main": {
    "temp": 292.98,
    "feels_like": 293.24,
    "temp_min": 290.33,
    "temp_max": 294.86,
    "pressure": 1012,
    "humidity": 85
  },
  "visibility": 10000,
  "wind": {
    "speed": 0.89,
    "deg": 173,
    "gust": 3.13
  },
  "clouds": {
    "all": 20
  },
  "dt": 1630815499,
  "sys": {
    "type": 2,
    "id": 2002287,
    "country": "US",
    "sunrise": 1630838461,
    "sunset": 1630884774
  },
  "timezone": -14400,
  "id": 4140963,
  "name": "Washington D.C.",
  "cod": 200
}
