{
  "coord": {
    "lon": -77.0364,
    "lat": 38.8951
  },
  "weather": [
    {
      "id": 501,
      "main": "Rain",
      "description": "moderate rain",
      "icon": "10n"
    },
    {
      "id": 701,
      "main": "Mist",
      "description": "mist",
      "icon": "50n"
    }
  ],
  "base": "stations",
  "main": {
    "temp": 276.14,
    "feels_like": 273.51,
    "temp_min": 273.37,
    "temp_max": 278.12,
    "pressure": 993,
    "humidity": 93
  },
  "visibility": 8047,
  "wind": {
    "speed": 2.68,
    "deg": 22,
    "gust": 8.05
  },
  "rain": {
    "1h": 3.16
  },
  "clouds": {
    "all": 100
  },
  "dt": 1642389014,
  "sys": {
    "type": 2,
    "id": 2002287,
    "country": "US",
    "sunrise": 1642335883,
    "sunset": 1642371043
  },
  "timezone": -18000,
  "id": 4140963,
  "name": "Washington D.C.",
  "cod": 200
}
