{
  "coord": {
    "lon": -77.0364,
    "lat": 38.8951
  },
  "weather": [
    {
      "id": 801,
      "main": "Clouds",
      "description": "few clouds",
      "icon": "02n"
    }
  ],
  "base": "stations",
  "main": {
    "temp": 271.19,
    "feels_like": 271.19,
    "temp_min": 268.16,
    "temp_max": 273.83,
    "pressure": 1018,
    "humidity": 77
  },
  "visibility": 10000,
  "wind": {
    "speed": 0,
    "deg": 0
  },
  "clouds": {
    "all": 20
  },
  "dt": 1644401559,
  "sys": {
    "type": 2,
    "id": 2034471,
    "country": "US",
    "sunrise": 1644408390,
    "sunset": 1644446300
  },
  "timezone": -18000,
  "id": 4140963,
  "name": "Washington D.C.",
  "cod": 200
}
