{
  "coord": {
    "lon": -77.0364,
    "lat": 38.8951
  },
  "weather": [
    {
      "id": 804,
      "main": "Clouds",
      "description": "overcast clouds",
      "icon": "04n"
    }
  ],
  "base": "stations",
  "main": {
    "temp": 287.28,
    "feels_like": 287.1,
    "temp_min": 283.14,
    "temp_max": 289.6,
    "pressure": 1014,
    "humidity": 90
  },
  "visibility": 10000,
  "wind": {
    "speed": 2.24,
    "deg": 191,
    "gust": 7.15
  },
  "clouds": {
    "all": 100
  },
  "dt": 1643947722,
  "sys": {
    "type": 2,
    "id": 2002287,
    "country": "US",
    "sunrise": 1643890355,
    "sunset": 1643927479
  },
  "timezone": -18000,
  "id": 4140963,
  "name": "Washington D.C.",
  "cod": 200
}
