{
  "coord": {
    "lon": -77.0364,
    "lat": 38.8951
  },
  "weather": [
    {
      "id": 804,
      "main": "Clouds",
      "description": "overcast clouds",
      "icon": "04d"
    }
  ],
  "base": "stations",
  "main": {
    "temp": 294.2,
    "feels_like": 294.68,
    "temp_min": 292.7,
    "temp_max": 295.99,
    "pressure": 1025,
    "humidity": 89
  },
  "visibility": 10000,
  "wind": {
    "speed": 0.89,
    "deg": 38,
    "gust": 1.79
  },
  "clouds": {
    "all": 90
  },
  "dt": 1633543944,
  "sys": {
    "type": 2,
    "id": 2002287,
    "country": "US",
    "sunrise": 1633518530,
    "sunset": 1633560195
  },
  "timezone": -14400,
  "id": 4140963,
  "name": "Washington D.C.",
  "cod": 200
}
