{
  "coord": {
    "lon": -77.0364,
    "lat": 38.8951
  },
  "weather": [
    {
      "id": 802,
      "main": "Clouds",
      "description": "scattered clouds",
      "icon": "03d"
    }
  ],
  "base": "stations",
  "main": {
    "temp": 283.66,
    "feels_like": 281.97,
    "temp_min": 282.24,
    "temp_max": 284.8,
    "pressure": 1020,
    "humidity": 46
  },
  "visibility": 10000,
  "wind": {
    "speed": 5.66,
    "deg": 340,
    "gust": 10.29
  },
  "clouds": {
    "all": 40
  },
  "dt": 1650201732,
  "sys": {
    "type": 2,
    "id": 2002287,
    "country": "US",
    "sunrise": 1650191314,
    "sunset": 1650239183
  },
  "timezone": -14400,
  "id": 4140963,
  "name": "Washington D.C.",
  "cod": 200
}
