{
  "coord": {
    "lon": -77.0364,
    "lat": 38.8951
  },
  "weather": [
    {
      "id": 501,
      "main": "Rain",
      "description": "moderate rain",
      "icon": "10d"
    },
    {
      "id": 701,
      "main": "Mist",
      "description": "mist",
      "icon": "50d"
    }
  ],
  "base": "stations",
  "main": {
    "temp": 287.55,
    "feels_like": 287.5,
    "temp_min": 284.78,
    "temp_max": 288.77,
    "pressure": 1007,
    "humidity": 94
  },
  "visibility": 3219,
  "wind": {
    "speed": 1.54,
    "deg": 210
  },
  "rain": {
    "1h": 1.1
  },
  "clouds": {
    "all": 90
  },
  "dt": 1641054144,
  "sys": {
    "type": 2,
    "id": 2002287,
    "country": "US",
    "sunrise": 1641040003,
    "sunset": 1641074186
  },
  "timezone": -18000,
  "id": 4140963,
  "name": "Washington D.C.",
  "cod": 200
}
