{
  "coord": {
    "lon": -77.0364,
    "lat": 38.8951
  },
  "weather": [
    {
      "id": 803,
      "main": "Clouds",
      "description": "broken clouds",
      "icon": "04n"
    }
  ],
  "base": "stations",
  "main": {
    "temp": 294.06,
    "feels_like": 294.5,
    "temp_min": 292.34,
    "temp_max": 295.68,
    "pressure": 1015,
    "humidity": 88
  },
  "visibility": 10000,
  "wind": {
    "speed": 1.34,
    "deg": 32,
    "gust": 2.24
  },
  "clouds": {
    "all": 75
  },
  "dt": 1628389360,
  "sys": {
    "type": 2,
    "id": 2002287,
    "country": "US",
    "sunrise": 1628331283,
    "sunset": 1628381585
  },
  "timezone": -14400,
  "id": 4140963,
  "name": "Washington D.C.",
  "cod": 200
}
