{
  "coord": {
    "lon": -77.0364,
    "lat": 38.8951
  },
  "weather": [
    {
      "id": 800,
      "main": "Clear",
      "description": "clear sky",
      "icon": "01n"
    }
  ],
  "base": "stations",
  "main": {
    "temp": 282.04,
    "feels_like": 282.04,
    "temp_min": 279.16,
    "temp_max": 285.12,
    "pressure": 1019,
    "humidity": 81
  },
  "visibility": 10000,
  "wind": {
    "speed": 0,
    "deg": 0
  },
  "clouds": {
    "all": 1
  },
  "dt": 1634620128,
  "sys": {
    "type": 1,
    "id": 3787,
    "country": "US",
    "sunrise": 1634642499,
    "sunset": 1634682248
  },
  "timezone": -14400,
  "id": 4140963,
  "name": "Washington D.C.",
  "cod": 200
}
