{
  "coord": {
    "lon": -77.0364,
    "lat": 38.8951
  },
  "weather": [
    {
      "id": 801,
      "main": "Clouds",
      "description": "few clouds",
      "icon": "02d"
    }
  ],
  "base": "stations",
  "main": {
    "temp": 290.05,
    "feels_like": 288.66,
    "temp_min": 286.89,
    "temp_max": 291.77,
    "pressure": 1012,
    "humidity": 33
  },
  "visibility": 10000,
  "wind": {
    "speed": 9.77,
    "deg": 210,
    "gust": 12.35
  },
  "clouds": {
    "all": 20
  },
  "dt": 1644603355,
  "sys": {
    "type": 2,
    "id": 2002287,
    "country": "US",
    "sunrise": 1644581057,
    "sunset": 1644619239
  },
  "timezone": -18000,
  "id": 4140963,
  "name": "Washington D.C.",
  "cod": 200
}
