{
  "coord": {
    "lon": -77.0364,
    "lat": 38.8951
  },
  "weather": [
    {
      "id": 800,
      "main": "Clear",
      "description": "clear sky",
      "icon": "01n"
    }
  ],
  "base": "stations",
  "main": {
    "temp": 278.7,
    "feels_like": 276.64,
    "temp_min": 275.42,
    "temp_max": 281.4,
    "pressure": 1022,
    "humidity": 61
  },
  "visibility": 10000,
  "wind": {
    "speed": 2.57,
    "deg": 260
  },
  "clouds": {
    "all": 0
  },
  "dt": 1647860843,
  "sys": {
    "type": 2,
    "id": 2034471,
    "country": "US",
    "sunrise": 1647861003,
    "sunset": 1647904831
  },
  "timezone": -14400,
  "id": 4140963,
  "name": "Washington D.C.",
  "cod": 200
}
