{
  "coord": {
    "lon": -77.0364,
    "lat": 38.8951
  },
  "weather": [
    {
      "id": 800,
      "main": "Clear",
      "description": "clear sky",
      "icon": "01n"
    }
  ],
  "base": "stations",
  "main": {
    "temp": 282.03,
    "feels_like": 280.99,
    "temp_min": 277.16,
    "temp_max": 285.21,
    "pressure": 1020,
    "humidity": 67
  },
  "visibility": 10000,
  "wind": {
    "speed": 2.06,
    "deg": 180
  },
  "clouds": {
    "all": 0
  },
  "dt": 1647418629,
  "sys": {
    "type": 2,
    "id": 2002287,
    "country": "US",
    "sunrise": 1647429477,
    "sunset": 1647472540
  },
  "timezone": -14400,
  "id": 4140963,
  "name": "Washington D.C.",
  "cod": 200
}
