{
  "coord": {
    "lon": -77.0364,
    "lat": 38.8951
  },
  "weather": [
    {
      "id": 803,
      "main": "Clouds",
      "description": "broken clouds",
      "icon": "04d"
    }
  ],
  "base": "stations",
  "main": {
    "temp": 293.54,
    "feels_like": 293.93,
    "temp_min": 291.99,
    "temp_max": 294.93,
    "pressure": 1011,
    "humidity": 88
  },
  "visibility": 10000,
  "wind": {
    "speed": 0.45,
    "deg": 211,
    "gust": 3.13
  },
  "clouds": {
    "all": 75
  },
  "dt": 1633345819,
  "sys": {
    "type": 2,
    "id": 2002287,
    "country": "US",
    "sunrise": 1633345617,
    "sunset": 1633387582
  },
  "timezone": -14400,
  "id": 4140963,
  "name": "Washington D.C.",
  "cod": 200
}
